ai/backend/kernel/VERSION
ai/backend/kernel/__init__.py
ai/backend/kernel/__main__.py
ai/backend/kernel/base.py
ai/backend/kernel/compat.py
ai/backend/kernel/exception.py
ai/backend/kernel/intrinsic.py
ai/backend/kernel/jupyter_client.py
ai/backend/kernel/logging.py
ai/backend/kernel/service.py
ai/backend/kernel/service_actions.py
ai/backend/kernel/terminal.py
ai/backend/kernel/utils.py
ai/backend/kernel/app/__init__.py
ai/backend/kernel/python/__init__.py
ai/backend/kernel/python/sitecustomize.py
ai/backend/kernel/python/types.py
ai/backend/kernel/python/drawing/__init__.py
ai/backend/kernel/python/drawing/canvas.py
ai/backend/kernel/python/drawing/color.py
ai/backend/kernel/python/drawing/encoding.py
ai/backend/kernel/python/drawing/turtle.py
ai/backend/kernel/vendor/__init__.py
ai/backend/kernel/vendor/aws_polly/__init__.py
ai/backend/kernel/vendor/aws_polly/inproc.py
ai/backend/kernel/vendor/h2o/__init__.py
backend_ai_kernel-26.1.0.dist-info/METADATA
backend_ai_kernel-26.1.0.dist-info/WHEEL
backend_ai_kernel-26.1.0.dist-info/namespace_packages.txt
backend_ai_kernel-26.1.0.dist-info/top_level.txt
backend_ai_kernel-26.1.0.dist-info/RECORD
