Metadata-Version: 2.4
Name: backend.ai-kernel
Version: 26.1.0
Summary: Backend.AI Kernel Runner
Home-page: https://github.com/lablup/backend.ai
Author: Lablup Inc. and contributors
License: LGPLv3
Project-URL: Documentation, https://docs.backend.ai/
Project-URL: Source, https://github.com/lablup/backend.ai
Classifier: Intended Audience :: Developers
Classifier: Operating System :: MacOS :: MacOS X
Classifier: Operating System :: POSIX :: Linux
Classifier: Programming Language :: Python
Classifier: Programming Language :: Python :: 3
Classifier: Environment :: No Input/Output (Daemon)
Classifier: Topic :: Scientific/Engineering
Classifier: Topic :: Software Development
Classifier: Development Status :: 5 - Production/Stable
Classifier: Programming Language :: Python :: 3.13
Classifier: License :: OSI Approved :: GNU Lesser General Public License v3 or later (LGPLv3+)
Requires-Python: >=3.13,<3.14
Requires-Dist: attrs>=25.3
Requires-Dist: boto3~=1.35
Requires-Dist: janus~=2.0
Requires-Dist: jupyter-client>=8.6
Requires-Dist: msgpack~=1.1.0
Requires-Dist: namedlist~=1.8
Requires-Dist: pyzmq~=26.4
Requires-Dist: types-six
Dynamic: author
Dynamic: classifier
Dynamic: description
Dynamic: description-content-type
Dynamic: home-page
Dynamic: license
Dynamic: project-url
Dynamic: requires-dist
Dynamic: requires-python
Dynamic: summary
